{
  "formatVersion": 1,
  "database": {
    "version": 4,
    "identityHash": "9af8f924117408e52ed7ccf95fb05ec6",
    "entities": [
      {
        "tableName": "contacts",
        "createSql": "CREATE TABLE IF NOT EXISTS `${TABLE_NAME}` (`id` TEXT NOT NULL, `displayName` TEXT NOT NULL, `phone` TEXT NOT NULL, `email` TEXT NOT NULL, `company` TEXT NOT NULL, `title` TEXT NOT NULL, `website` TEXT NOT NULL, `bio` TEXT NOT NULL, `avatarUri` TEXT NOT NULL, `sourceEndpointId` TEXT NOT NULL, `rssiAtExchange` INTEGER NOT NULL, `receivedAt` INTEGER NOT NULL, `isFavorite` INTEGER NOT NULL, `notes` TEXT NOT NULL, `identityKeyHash` TEXT, PRIMARY KEY(`id`))",
        "fields": [
          {
            "fieldPath": "id",
            "columnName": "id",
            "affinity": "TEXT",
            "notNull": true
          },
          {
            "fieldPath": "displayName",
            "columnName": "displayName",
            "affinity": "TEXT",
            "notNull": true
          },
          {
            "fieldPath": "phone",
            "columnName": "phone",
            "affinity": "TEXT",
            "notNull": true
          },
          {
            "fieldPath": "email",
            "columnName": "email",
            "affinity": "TEXT",
            "notNull": true
          },
          {
            "fieldPath": "company",
            "columnName": "company",
            "affinity": "TEXT",
            "notNull": true
          },
          {
            "fieldPath": "title",
            "columnName": "title",
            "affinity": "TEXT",
            "notNull": true
          },
          {
            "fieldPath": "website",
            "columnName": "website",
            "affinity": "TEXT",
            "notNull": true
          },
          {
            "fieldPath": "bio",
            "columnName": "bio",
            "affinity": "TEXT",
            "notNull": true
          },
          {
            "fieldPath": "avatarUri",
            "columnName": "avatarUri",
            "affinity": "TEXT",
            "notNull": true
          },
          {
            "fieldPath": "sourceEndpointId",
            "columnName": "sourceEndpointId",
            "affinity": "TEXT",
            "notNull": true
          },
          {
            "fieldPath": "rssiAtExchange",
            "columnName": "rssiAtExchange",
            "affinity": "INTEGER",
            "notNull": true
          },
          {
            "fieldPath": "receivedAt",
            "columnName": "receivedAt",
            "affinity": "INTEGER",
            "notNull": true
          },
          {
            "fieldPath": "isFavorite",
            "columnName": "isFavorite",
            "affinity": "INTEGER",
            "notNull": true
          },
          {
            "fieldPath": "notes",
            "columnName": "notes",
            "affinity": "TEXT",
            "notNull": true
          },
          {
            "fieldPath": "identityKeyHash",
            "columnName": "identityKeyHash",
            "affinity": "TEXT",
            "notNull": false
          }
        ],
        "primaryKey": {
          "autoGenerate": false,
          "columnNames": [
            "id"
          ]
        },
        "indices": [],
        "foreignKeys": []
      },
      {
        "tableName": "profile",
        "createSql": "CREATE TABLE IF NOT EXISTS `${TABLE_NAME}` (`id` TEXT NOT NULL, `displayName` TEXT NOT NULL, `phone` TEXT NOT NULL, `email` TEXT NOT NULL, `company` TEXT NOT NULL, `title` TEXT NOT NULL, `website` TEXT NOT NULL, `bio` TEXT NOT NULL, `shareFields` TEXT NOT NULL, `avatarUri` TEXT NOT NULL, `createdAt` INTEGER NOT NULL, `updatedAt` INTEGER NOT NULL, PRIMARY KEY(`id`))",
        "fields": [
          {
            "fieldPath": "id",
            "columnName": "id",
            "affinity": "TEXT",
            "notNull": true
          },
          {
            "fieldPath": "displayName",
            "columnName": "displayName",
            "affinity": "TEXT",
            "notNull": true
          },
          {
            "fieldPath": "phone",
            "columnName": "phone",
            "affinity": "TEXT",
            "notNull": true
          },
          {
            "fieldPath": "email",
            "columnName": "email",
            "affinity": "TEXT",
            "notNull": true
          },
          {
            "fieldPath": "company",
            "columnName": "company",
            "affinity": "TEXT",
            "notNull": true
          },
          {
            "fieldPath": "title",
            "columnName": "title",
            "affinity": "TEXT",
            "notNull": true
          },
          {
            "fieldPath": "website",
            "columnName": "website",
            "affinity": "TEXT",
            "notNull": true
          },
          {
            "fieldPath": "bio",
            "columnName": "bio",
            "affinity": "TEXT",
            "notNull": true
          },
          {
            "fieldPath": "shareFields",
            "columnName": "shareFields",
            "affinity": "TEXT",
            "notNull": true
          },
          {
            "fieldPath": "avatarUri",
            "columnName": "avatarUri",
            "affinity": "TEXT",
            "notNull": true
          },
          {
            "fieldPath": "createdAt",
            "columnName": "createdAt",
            "affinity": "INTEGER",
            "notNull": true
          },
          {
            "fieldPath": "updatedAt",
            "columnName": "updatedAt",
            "affinity": "INTEGER",
            "notNull": true
          }
        ],
        "primaryKey": {
          "autoGenerate": false,
          "columnNames": [
            "id"
          ]
        },
        "indices": [],
        "foreignKeys": []
      },
      {
        "tableName": "blocked_endpoints",
        "createSql": "CREATE TABLE IF NOT EXISTS `${TABLE_NAME}` (`endpointId` TEXT NOT NULL, `blockedAt` INTEGER NOT NULL, `note` TEXT NOT NULL, `identityKeyHash` TEXT, PRIMARY KEY(`endpointId`))",
        "fields": [
          {
            "fieldPath": "endpointId",
            "columnName": "endpointId",
            "affinity": "TEXT",
            "notNull": true
          },
          {
            "fieldPath": "blockedAt",
            "columnName": "blockedAt",
            "affinity": "INTEGER",
            "notNull": true
          },
          {
            "fieldPath": "note",
            "columnName": "note",
            "affinity": "TEXT",
            "notNull": true
          },
          {
            "fieldPath": "identityKeyHash",
            "columnName": "identityKeyHash",
            "affinity": "TEXT",
            "notNull": false
          }
        ],
        "primaryKey": {
          "autoGenerate": false,
          "columnNames": [
            "endpointId"
          ]
        },
        "indices": [],
        "foreignKeys": []
      },
      {
        "tableName": "known_peers",
        "createSql": "CREATE TABLE IF NOT EXISTS `${TABLE_NAME}` (`endpointId` TEXT NOT NULL, `identityPublicKeyBase64` TEXT NOT NULL, `firstSeenAt` INTEGER NOT NULL, `lastSeenAt` INTEGER NOT NULL, PRIMARY KEY(`endpointId`))",
        "fields": [
          {
            "fieldPath": "endpointId",
            "columnName": "endpointId",
            "affinity": "TEXT",
            "notNull": true
          },
          {
            "fieldPath": "identityPublicKeyBase64",
            "columnName": "identityPublicKeyBase64",
            "affinity": "TEXT",
            "notNull": true
          },
          {
            "fieldPath": "firstSeenAt",
            "columnName": "firstSeenAt",
            "affinity": "INTEGER",
            "notNull": true
          },
          {
            "fieldPath": "lastSeenAt",
            "columnName": "lastSeenAt",
            "affinity": "INTEGER",
            "notNull": true
          }
        ],
        "primaryKey": {
          "autoGenerate": false,
          "columnNames": [
            "endpointId"
          ]
        },
        "indices": [],
        "foreignKeys": []
      }
    ],
    "views": [],
    "setupQueries": [
      "CREATE TABLE IF NOT EXISTS room_master_table (id INTEGER PRIMARY KEY,identity_hash TEXT)",
      "INSERT OR REPLACE INTO room_master_table (id,identity_hash) VALUES(42, '9af8f924117408e52ed7ccf95fb05ec6')"
    ]
  }
}